ydt1363/__init__.py
ydt1363/frame.py
ydt1363/protocol.py
ydt1363/utils.py
ydt1363-0.1.1.dist-info/licenses/LICENSE
ydt1363-0.1.1.dist-info/METADATA
ydt1363-0.1.1.dist-info/WHEEL
ydt1363-0.1.1.dist-info/top_level.txt
ydt1363-0.1.1.dist-info/RECORD
